mlbee/__init__.py
mlbee/__main__.py
mlbee/__main__.py-
mlbee/alive_bar.py
mlbee/color_map.py
mlbee/cos_matrix2.py
mlbee/detect.py-
mlbee/gen_filename.py
mlbee/loadparas.py
mlbee/mlbee.py
mlbee/save_xlsx_tsv_csv.py
mlbee/text2lists.py-
mlbee/texts2pairs.py
mlbee-0.1.0a5.dist-info/entry_points.txt
mlbee-0.1.0a5.dist-info/LICENSE
mlbee-0.1.0a5.dist-info/WHEEL
mlbee-0.1.0a5.dist-info/METADATA
mlbee-0.1.0a5.dist-info/RECORD
